avdoc/__init__.py
avdoc/__main__.py
avdoc-0.5.1.dist-info/LICENSE
avdoc-0.5.1.dist-info/METADATA
avdoc-0.5.1.dist-info/WHEEL
avdoc-0.5.1.dist-info/entry_points.txt
avdoc-0.5.1.dist-info/RECORD
