Metadata-Version: 2.1
Name: avdoc
Version: 0.5.1
Summary: CLI tool to generate HTML documentation for an Apache Avro schema
Home-page: https://github.com/jeffbr13/avdoc
License: AGPL-3.0-or-later
Keywords: avro,avro-schema
Author: Ben Jeffrey
Author-email: mail@benjeffrey.net
Requires-Python: >=3.10,<4.0
Classifier: Development Status :: 3 - Alpha
Classifier: License :: OSI Approved :: GNU Affero General Public License v3 or later (AGPLv3+)
Classifier: Operating System :: MacOS
Classifier: Operating System :: POSIX :: Linux
Classifier: Programming Language :: Python :: 3
Classifier: Programming Language :: Python :: 3.10
Classifier: Programming Language :: Python :: 3.11
Classifier: Programming Language :: Python :: 3.12
Classifier: Programming Language :: Python :: 3.13
Classifier: Topic :: Documentation
Classifier: Topic :: Software Development
Classifier: Topic :: Software Development :: Documentation
Classifier: Topic :: Text Processing :: Markup :: HTML
Requires-Dist: avro (>=1.11.1,<2.0.0)
Requires-Dist: dominate (>=2.8.0,<3.0.0)
Requires-Dist: mistune (>=3.0.1,<4.0.0)
Requires-Dist: pygraphviz (>=1.11,<2.0)
Project-URL: Repository, https://github.com/jeffbr13/avdoc
